[
  {
    "testo": "L'intelletto possibile riceve le forme intelligibili come la materia riceve le forme fisiche.",
    "autore": "Tommaso d'Aquino"
  },
  {
    "testo": "La grazia non distrugge la natura, ma la perfeziona.",
    "autore": "Tommaso d'Aquino"
  },
  {
    "testo": "Chi non ama la sapienza non può essere felice.",
    "autore": "Tommaso d'Aquino"
  },
  {
    "testo": "Il bene comune vale più del bene privato.",
    "autore": "Tommaso d'Aquino"
  },
  {
    "testo": "L'amore è la forza che muove il sole e le altre stelle.",
    "autore": "Tommaso d'Aquino"
  },
  {
    "testo": "Credere è un atto dell'intelletto che aderisce alla verità divina.",
    "autore": "Tommaso d'Aquino"
  },
  {
    "testo": "La pace è la tranquillità dell'ordine.",
    "autore": "Sant'Agostino"
  },
  {
    "testo": "Il mondo è un libro e chi non viaggia ne legge solo una pagina.",
    "autore": "Sant'Agostino"
  },
  {
    "testo": "Signore, fammi casto, ma non ancora.",
    "autore": "Sant'Agostino"
  },
  {
    "testo": "Tardi ti amai, bellezza così antica e così nuova.",
    "autore": "Sant'Agostino"
  },
  {
    "testo": "Il nostro cuore non ha pace se non riposa in te.",
    "autore": "Sant'Agostino"
  },
  {
    "testo": "Ama e fa ciò che vuoi.",
    "autore": "Sant'Agostino"
  },
  {
    "testo": "Pecca fortiter — Pecca con coraggio, ma credi ancora più fortemente.",
    "autore": "Martino Lutero"
  },
  {
    "testo": "Chi non può vivere nella società è o un animale o un dio.",
    "autore": "Aristotele"
  },
  {
    "testo": "Il tempo è il miglior giudice di tutto.",
    "autore": "Proverbio scolastico"
  },
  {
    "testo": "La verità è adaequatio rei et intellectus — corrispondenza tra cosa e intelletto.",
    "autore": "Tommaso d'Aquino"
  },
  {
    "testo": "Chi conosce il fine conosce il cammino.",
    "autore": "Proverbio medievale"
  },
  {
    "testo": "Nihil est in intellectu quod prius non fuerit in sensu.",
    "autore": "Aristotele / Scolastica"
  },
  {
    "testo": "L'esperienza è maestra di ogni cosa.",
    "autore": "Giulio Cesare"
  },
  {
    "testo": "La filosofia è ancilla theologiae — serva della teologia.",
    "autore": "Proverbio scolastico"
  },
  {
    "testo": "Dei delitti e delle pene: la pena deve essere proporzionata al delitto.",
    "autore": "Cesare Beccaria"
  },
  {
    "testo": "La tortura è un mezzo sicuro per assolvere il robusto criminale e condannare il debole innocente.",
    "autore": "Cesare Beccaria"
  },
  {
    "testo": "Il fine della legge è la felicità del maggior numero di persone.",
    "autore": "Cesare Beccaria"
  },
  {
    "testo": "Quando vedo ardere il fuoco dei filosofi, mi riscaldo al loro calore.",
    "autore": "Giacomo Casanova"
  },
  {
    "testo": "La libertà di pensiero è il fondamento di ogni progresso civile.",
    "autore": "Pietro Verri"
  },
  {
    "testo": "Il commercio libero arricchisce le nazioni.",
    "autore": "Pietro Verri"
  },
  {
    "testo": "La ragione è la luce che illumina il cammino dell'uomo.",
    "autore": "Illuminismo"
  },
  {
    "testo": "Ecrasez l'infâme — Schiacciate l'infame superstizione.",
    "autore": "Voltaire"
  },
  {
    "testo": "Il coraggio della ragione è il primo dovere dell'uomo.",
    "autore": "Immanuel Kant"
  },
  {
    "testo": "Chi non pensa con la propria testa è schiavo del pensiero altrui.",
    "autore": "Anonimo illuminista"
  },
  {
    "testo": "Giovine Italia: unità, indipendenza, libertà.",
    "autore": "Giuseppe Mazzini"
  },
  {
    "testo": "Senza doveri non si hanno diritti.",
    "autore": "Giuseppe Mazzini"
  },
  {
    "testo": "L'Italia farà da sé quando gli italiani faranno da sé.",
    "autore": "Giuseppe Mazzini"
  },
  {
    "testo": "La patria non è il territorio: è l'insieme dei suoi cittadini.",
    "autore": "Giuseppe Mazzini"
  },
  {
    "testo": "Il pensiero è l'azione delle anime forti.",
    "autore": "Giuseppe Mazzini"
  },
  {
    "testo": "L'educazione è la prima base della moralità sociale.",
    "autore": "Giuseppe Mazzini"
  },
  {
    "testo": "I confini naturali dell'Italia sono le Alpi e il mare.",
    "autore": "Proverbio risorgimentale"
  },
  {
    "testo": "Il sangue versato per la patria non si dimentica mai.",
    "autore": "Proverbio patriottico"
  },
  {
    "testo": "Chi muore per la libertà ha vissuto pienamente.",
    "autore": "Proverbio risorgimentale"
  },
  {
    "testo": "L'unità d'Italia è il trionfo della civiltà sulla barbarie.",
    "autore": "Proverbio risorgimentale"
  },
  {
    "testo": "L'uomo è condannato ad essere libero.",
    "autore": "Jean-Paul Sartre"
  },
  {
    "testo": "Il problema di Dio è il problema dell'uomo.",
    "autore": "Paul Tillich"
  },
  {
    "testo": "L'essere è; il nulla non è.",
    "autore": "Martin Heidegger"
  },
  {
    "testo": "Il linguaggio è la casa dell'essere.",
    "autore": "Martin Heidegger"
  },
  {
    "testo": "Solo chi rischia di andare troppo lontano può scoprire quanto lontano si può andare.",
    "autore": "T.S. Eliot"
  },
  {
    "testo": "Il mondo è tutto ciò che accade.",
    "autore": "Ludwig Wittgenstein"
  },
  {
    "testo": "Su ciò di cui non si può parlare, si deve tacere.",
    "autore": "Ludwig Wittgenstein"
  },
  {
    "testo": "I limiti del mio linguaggio significano i limiti del mio mondo.",
    "autore": "Ludwig Wittgenstein"
  },
  {
    "testo": "Non esiste un fatto puro senza interpretazione.",
    "autore": "Friedrich Nietzsche"
  },
  {
    "testo": "La filosofia è la cura dell'anima.",
    "autore": "Epicuro"
  },
  {
    "testo": "L'uomo che domanda è già a metà del cammino della saggezza.",
    "autore": "Proverbio"
  },
  {
    "testo": "Il dubbio sistematico è il metodo della filosofia moderna.",
    "autore": "René Descartes"
  },
  {
    "testo": "Non si può capire l'uomo senza la sua storia.",
    "autore": "Wilhelm Dilthey"
  },
  {
    "testo": "La coscienza è sempre coscienza di qualcosa.",
    "autore": "Edmund Husserl"
  },
  {
    "testo": "L'essere umano è un animale simbolico.",
    "autore": "Ernst Cassirer"
  },
  {
    "testo": "La filosofia della pratica è la filosofia dell'azione.",
    "autore": "Antonio Gramsci"
  },
  {
    "testo": "Il pessimismo dell'intelletto e l'ottimismo della volontà.",
    "autore": "Antonio Gramsci"
  },
  {
    "testo": "La cultura è organizzazione, disciplina del proprio io interiore.",
    "autore": "Antonio Gramsci"
  },
  {
    "testo": "Tutti gli uomini sono intellettuali, ma non tutti svolgono questa funzione.",
    "autore": "Antonio Gramsci"
  },
  {
    "testo": "Il vecchio muore e il nuovo non riesce ancora a nascere.",
    "autore": "Antonio Gramsci"
  },
  {
    "testo": "Laddove c'era l'Es, deve subentrare l'Io.",
    "autore": "Sigmund Freud"
  },
  {
    "testo": "L'amore e il lavoro sono le fondamenta della nostra umanità.",
    "autore": "Sigmund Freud"
  },
  {
    "testo": "I sogni sono la via regia verso l'inconscio.",
    "autore": "Sigmund Freud"
  },
  {
    "testo": "La nevrosi è l'incapacità di tollerare l'ambiguità.",
    "autore": "Sigmund Freud"
  },
  {
    "testo": "Dove si ama poco, si critica molto.",
    "autore": "Sigmund Freud"
  },
  {
    "testo": "Il subconscio sa quello che la coscienza non vuole sapere.",
    "autore": "Carl Gustav Jung"
  },
  {
    "testo": "L'inconscio collettivo è il deposito dell'esperienza ancestrale.",
    "autore": "Carl Gustav Jung"
  },
  {
    "testo": "Uno non si illumina immaginando figure di luce, ma rendendo cosciente l'oscurità.",
    "autore": "Carl Gustav Jung"
  },
  {
    "testo": "Il tuo compito non è cercare l'amore, ma trovare le barriere che hai costruito contro di esso.",
    "autore": "Rumi / Carl Gustav Jung"
  },
  {
    "testo": "Quello che nega o sopprime finisce per tornare più forte.",
    "autore": "Carl Gustav Jung"
  },
  {
    "testo": "L'uomo non è mai pienamente libero dal suo passato.",
    "autore": "Alfred Adler"
  },
  {
    "testo": "Il senso della vita è il contributo che si dà agli altri.",
    "autore": "Viktor Frankl"
  },
  {
    "testo": "Chi ha un perché da vivere può sopportare quasi qualsiasi come.",
    "autore": "Viktor Frankl"
  },
  {
    "testo": "Tra stimolo e risposta c'è uno spazio. In quello spazio sta la nostra libertà.",
    "autore": "Viktor Frankl"
  },
  {
    "testo": "Non possiamo evitare la sofferenza, ma possiamo scegliere come risponderle.",
    "autore": "Viktor Frankl"
  },
  {
    "testo": "La vita ci chiede domande: sta a noi trovare le risposte.",
    "autore": "Viktor Frankl"
  },
  {
    "testo": "L'uomo che ha uno scopo può sopportare qualsiasi circostanza.",
    "autore": "Viktor Frankl"
  },
  {
    "testo": "La salute mentale si basa su un certo grado di tensione tra ciò che si è e ciò che si dovrebbe diventare.",
    "autore": "Viktor Frankl"
  },
  {
    "testo": "L'autorealizzazione non può essere raggiunta come fine a se stessa.",
    "autore": "Abraham Maslow"
  },
  {
    "testo": "Se sei intenzionalmente meno di quello che puoi essere, sarai infelice per il resto della vita.",
    "autore": "Abraham Maslow"
  },
  {
    "testo": "Un musicista deve fare musica, un artista deve dipingere, un poeta deve scrivere.",
    "autore": "Abraham Maslow"
  },
  {
    "testo": "Chi non investe in se stesso non può aspettarsi investimenti dagli altri.",
    "autore": "Anonimo"
  },
  {
    "testo": "Il capitale più importante è quello umano.",
    "autore": "Anonimo"
  },
  {
    "testo": "L'innovazione distingue un leader da un seguace.",
    "autore": "Steve Jobs"
  },
  {
    "testo": "Non è abbastanza fare del tuo meglio; devi sapere cosa fare e poi fare del tuo meglio.",
    "autore": "W. Edwards Deming"
  },
  {
    "testo": "Il cliente non è sempre il re, ma è sempre il cliente.",
    "autore": "Proverbio commerciale"
  },
  {
    "testo": "Chi non migliora, peggiora.",
    "autore": "Proverbio aziendale"
  },
  {
    "testo": "La qualità non si controlla, si costruisce.",
    "autore": "W. Edwards Deming"
  },
  {
    "testo": "Non puoi gestire ciò che non puoi misurare.",
    "autore": "Peter Drucker"
  },
  {
    "testo": "Fare le cose giuste è più importante che fare le cose bene.",
    "autore": "Peter Drucker"
  },
  {
    "testo": "Il miglior piano è quello che si esegue.",
    "autore": "George S. Patton"
  },
  {
    "testo": "L'eccellenza è un'abitudine, non un evento.",
    "autore": "Aristotele"
  },
  {
    "testo": "Chi non sa delegare non sa crescere.",
    "autore": "Anonimo"
  },
  {
    "testo": "Il prezzo è quello che paghi, il valore è quello che ottieni.",
    "autore": "Warren Buffett"
  },
  {
    "testo": "Regola numero uno: non perdere mai denaro. Regola numero due: non dimenticare mai la regola numero uno.",
    "autore": "Warren Buffett"
  },
  {
    "testo": "Il rischio viene dal non sapere quello che stai facendo.",
    "autore": "Warren Buffett"
  },
  {
    "testo": "Investire in te stesso è il miglior investimento che tu possa fare.",
    "autore": "Warren Buffett"
  },
  {
    "testo": "La reputazione richiede vent'anni per costruirsi e cinque minuti per distruggersi.",
    "autore": "Warren Buffett"
  },
  {
    "testo": "Chi lavora solo per i soldi è già povero.",
    "autore": "Anonimo"
  },
  {
    "testo": "Il talento senza disciplina è come un polpo su rollerblade.",
    "autore": "H. Jackson Brown Jr."
  },
  {
    "testo": "Sii avido quando gli altri hanno paura e abbi paura quando gli altri sono avidi.",
    "autore": "Warren Buffett"
  },
  {
    "testo": "La bellezza è nel gesto quotidiano.",
    "autore": "Anonimo"
  },
  {
    "testo": "L'arte non riproduce il visibile: rende visibile.",
    "autore": "Paul Klee"
  },
  {
    "testo": "La poesia è semplicemente la più bella, la più immortale, la più felice delle arti.",
    "autore": "Percy Bysshe Shelley"
  },
  {
    "testo": "La pittura è la poesia che si vede e non si sente.",
    "autore": "Leonardo da Vinci"
  },
  {
    "testo": "Un'opera d'arte è il grido di chi sente intensamente la vita.",
    "autore": "Edvard Munch"
  },
  {
    "testo": "L'arte è il modo in cui l'uomo trasforma il dolore in bellezza.",
    "autore": "Anonimo"
  },
  {
    "testo": "La fotografia è la verità e il cinema è ventiquattro volte al secondo la verità.",
    "autore": "Jean-Luc Godard"
  },
  {
    "testo": "La scrittura è un atto di fede.",
    "autore": "E.B. White"
  },
  {
    "testo": "I romanzi sono specchi che camminano lungo una strada principale.",
    "autore": "Stendhal"
  },
  {
    "testo": "La letteratura è l'arte di scoprire qualcosa di straordinario nell'ordinario.",
    "autore": "Anonimo"
  },
  {
    "testo": "Ogni storia d'amore è unica e universale allo stesso tempo.",
    "autore": "Anonimo"
  },
  {
    "testo": "Il teatro è lo specchio deformante della realtà.",
    "autore": "Anonimo"
  },
  {
    "testo": "La musica esprime ciò che non può essere detto né taciuto.",
    "autore": "Victor Hugo"
  },
  {
    "testo": "Un libro ben scritto è il sangue del maestro che lo ha scritto.",
    "autore": "John Milton"
  },
  {
    "testo": "La poesia è la più pura delle arti perché non serve a niente e vale tutto.",
    "autore": "Anonimo"
  },
  {
    "testo": "L'arte non ha confini di nazione, lingua o tempo.",
    "autore": "Anonimo"
  },
  {
    "testo": "Chi crea arte dona immortalità.",
    "autore": "Orazio"
  },
  {
    "testo": "La critica d'arte è la prosecuzione dell'arte con altri mezzi.",
    "autore": "Anonimo"
  },
  {
    "testo": "L'ispirazione è la scintilla; il lavoro è il fuoco.",
    "autore": "Anonimo"
  },
  {
    "testo": "Chi non sa apprezzare l'arte non sa apprezzare la vita.",
    "autore": "Anonimo"
  },
  {
    "testo": "La scienza è un modo di non illudersi.",
    "autore": "Richard Feynman"
  },
  {
    "testo": "Se non riesci a spiegarlo semplicemente, non lo hai capito abbastanza bene.",
    "autore": "Albert Einstein"
  },
  {
    "testo": "La scienza senza la coscienza è la rovina dell'anima.",
    "autore": "François Rabelais"
  },
  {
    "testo": "Il progresso scientifico è la rotazione del quadro non il suo rovesciamento.",
    "autore": "Thomas Kuhn"
  },
  {
    "testo": "Una teoria che spiega tutto non spiega nulla.",
    "autore": "Karl Popper"
  },
  {
    "testo": "La scienza avanza di funerale in funerale.",
    "autore": "Max Planck"
  },
  {
    "testo": "Il paradosso è il cammino della creatività.",
    "autore": "Niels Bohr"
  },
  {
    "testo": "Dio non gioca a dadi con l'universo.",
    "autore": "Albert Einstein"
  },
  {
    "testo": "L'immaginazione è tutto. È l'anteprima delle prossime attrazioni della vita.",
    "autore": "Albert Einstein"
  },
  {
    "testo": "La distinzione tra passato, presente e futuro è solo una tenace illusione.",
    "autore": "Albert Einstein"
  },
  {
    "testo": "La realtà è ciò che rimane quando smetti di credere in essa.",
    "autore": "Philip K. Dick"
  },
  {
    "testo": "L'universo non è solo più strano di quanto supponiamo, è più strano di quanto possiamo supporre.",
    "autore": "J.B.S. Haldane"
  },
  {
    "testo": "La complessità nasce dalla semplicità.",
    "autore": "Anonimo"
  },
  {
    "testo": "La natura opera sempre nel modo più breve possibile.",
    "autore": "Galileo Galilei"
  },
  {
    "testo": "Ogni cosa è possibile: la questione è quanto è probabile.",
    "autore": "Anonimo scientifico"
  },
  {
    "testo": "La storia è il racconto di come gli uomini hanno lottato per il potere.",
    "autore": "Jacob Burckhardt"
  },
  {
    "testo": "Ogni grande crisi storica è anche un'opportunità.",
    "autore": "Anonimo"
  },
  {
    "testo": "Le rivoluzioni si fanno con i sogni, si governano con la realtà.",
    "autore": "Anonimo"
  },
  {
    "testo": "Chi controlla il passato controlla il futuro.",
    "autore": "George Orwell"
  },
  {
    "testo": "La storia non assolve nessuno: chiede conto a tutti.",
    "autore": "Anonimo"
  },
  {
    "testo": "I grandi movimenti storici partono sempre dal basso.",
    "autore": "Anonimo"
  },
  {
    "testo": "Non è il re che fa la storia: è il popolo.",
    "autore": "Leon Tolstoy"
  },
  {
    "testo": "La pace è il frutto maturo della giustizia.",
    "autore": "Proverbio"
  },
  {
    "testo": "Ogni costituzione vale quanto i cittadini che la difendono.",
    "autore": "Anonimo"
  },
  {
    "testo": "La democrazia non è uno stato: è un processo continuo.",
    "autore": "Anonimo"
  },
  {
    "testo": "Chi non partecipa alla vita pubblica è condannato ad essere governato dai peggiori.",
    "autore": "Platone"
  },
  {
    "testo": "Il potere logora chi non ce l'ha.",
    "autore": "Giulio Andreotti"
  },
  {
    "testo": "Un popolo senza memoria è un popolo senza futuro.",
    "autore": "Anonimo"
  },
  {
    "testo": "La storia non la fanno i grandi uomini: la fanno i popoli.",
    "autore": "Anonimo"
  },
  {
    "testo": "Chi dimentica il passato è condannato a riviverlo.",
    "autore": "George Santayana"
  },
  {
    "testo": "Quello che non vuoi sia fatto a te, non farlo agli altri.",
    "autore": "Confucio / Regola d'oro"
  },
  {
    "testo": "Non fare del male a nessun essere vivente.",
    "autore": "Mahavira / Giainismo"
  },
  {
    "testo": "La via di mezzo è la via della saggezza.",
    "autore": "Buddha"
  },
  {
    "testo": "L'amore per Dio e il servizio agli uomini: ecco la religione.",
    "autore": "Mahatma Gandhi"
  },
  {
    "testo": "Dio è amore: chi vive nell'amore vive in Dio.",
    "autore": "Prima Lettera di Giovanni"
  },
  {
    "testo": "Non c'è costrizione nella religione.",
    "autore": "Corano 2:256"
  },
  {
    "testo": "L'uomo non è grande quando è in pinocchio davanti a Dio, ma quando si rialza.",
    "autore": "Victor Hugo"
  },
  {
    "testo": "La fede senza le opere è morta.",
    "autore": "Lettera di Giacomo 2:26"
  },
  {
    "testo": "Chi cerca Dio con cuore puro lo trova.",
    "autore": "Proverbio spirituale"
  },
  {
    "testo": "Tutte le strade portano a Dio, anche quelle che sembrano allontanarsene.",
    "autore": "Proverbio mistico"
  },
  {
    "testo": "Il vero monaco è colui che non fa distinzione tra gli esseri.",
    "autore": "Proverbio buddhista"
  },
  {
    "testo": "La preghiera più autentica è la vita vissuta bene.",
    "autore": "Anonimo"
  },
  {
    "testo": "Dio parla nel silenzio del cuore.",
    "autore": "Madre Teresa di Calcutta"
  },
  {
    "testo": "Ogni religione è un sentiero verso la stessa montagna.",
    "autore": "Proverbio"
  },
  {
    "testo": "L'amore del prossimo è la misura dell'amore di Dio.",
    "autore": "Proverbio cristiano"
  },
  {
    "testo": "Chi ha tempo non aspetti tempo.",
    "autore": "Proverbio toscano"
  },
  {
    "testo": "Meglio un giorno in testa al leone che cento da pecore.",
    "autore": "Proverbio toscano"
  },
  {
    "testo": "Il medico pietoso fa la piaga verminosa.",
    "autore": "Proverbio toscano"
  },
  {
    "testo": "Non dare all'asino la biada di troppo.",
    "autore": "Proverbio toscano"
  },
  {
    "testo": "Paese che vai usanza che trovi.",
    "autore": "Proverbio italiano"
  },
  {
    "testo": "Ride bene chi ride l'ultimo.",
    "autore": "Proverbio italiano"
  },
  {
    "testo": "L'abito non fa il monaco, ma aiuta.",
    "autore": "Proverbio italiano"
  },
  {
    "testo": "Tra i due litiganti, il terzo gode.",
    "autore": "Proverbio italiano"
  },
  {
    "testo": "A mali estremi, estremi rimedi.",
    "autore": "Proverbio italiano"
  },
  {
    "testo": "Chi va piano va sano e lontano.",
    "autore": "Proverbio italiano"
  },
  {
    "testo": "Non si può avere capra e cavoli.",
    "autore": "Proverbio italiano"
  },
  {
    "testo": "Il troppo stroppia.",
    "autore": "Proverbio italiano"
  },
  {
    "testo": "Meglio un uovo oggi che una gallina domani.",
    "autore": "Proverbio italiano"
  },
  {
    "testo": "Tanto va la gatta al lardo che ci lascia lo zampino.",
    "autore": "Proverbio italiano"
  },
  {
    "testo": "Acqua in bocca.",
    "autore": "Proverbio italiano"
  },
  {
    "testo": "Non fare il passo più lungo della gamba.",
    "autore": "Proverbio italiano"
  },
  {
    "testo": "Gallina vecchia fa buon brodo.",
    "autore": "Proverbio italiano"
  },
  {
    "testo": "In bocca al lupo: crepi.",
    "autore": "Proverbio teatrale italiano"
  },
  {
    "testo": "Chi rompe paga e i cocci son suoi.",
    "autore": "Proverbio italiano"
  },
  {
    "testo": "Occhio per occhio, dente per dente.",
    "autore": "Proverbio biblico"
  },
  {
    "testo": "L'anima è lo specchio dell'universo.",
    "autore": "Gottfried Leibniz"
  },
  {
    "testo": "Conosci la tua anima e conoscerai il mondo.",
    "autore": "Proverbio"
  },
  {
    "testo": "L'anima non invecchia mai: è il corpo che la limita.",
    "autore": "Anonimo"
  },
  {
    "testo": "Chi cura l'anima non dimentica il corpo, ma chi cura solo il corpo dimentica l'anima.",
    "autore": "Platone"
  },
  {
    "testo": "Il corpo è la prigione o il tempio dell'anima, a seconda di come lo usi.",
    "autore": "Platone"
  },
  {
    "testo": "L'anima ha bisogno di silenzio come il corpo ha bisogno di cibo.",
    "autore": "Anonimo"
  },
  {
    "testo": "Le ferite dell'anima guariscono più lentamente di quelle del corpo.",
    "autore": "Proverbio"
  },
  {
    "testo": "Chi purifica l'anima purifica il mondo.",
    "autore": "Proverbio"
  },
  {
    "testo": "L'anima è il nucleo immortale di ogni essere.",
    "autore": "Platone"
  },
  {
    "testo": "Chi nutre l'anima non ha mai fame.",
    "autore": "Anonimo"
  },
  {
    "testo": "La giustizia è la costante e perpetua volontà di dare a ciascuno il suo.",
    "autore": "Ulpiano"
  },
  {
    "testo": "Fiat justitia, pereat mundus — Si faccia giustizia anche se il mondo perisce.",
    "autore": "Imperatore Ferdinando I"
  },
  {
    "testo": "La giustizia ritardata è giustizia negata.",
    "autore": "William Gladstone"
  },
  {
    "testo": "Non vi è pace senza giustizia.",
    "autore": "Proverbio"
  },
  {
    "testo": "Chi giudica senza ascoltare non è un giudice, è un tiranno.",
    "autore": "Anonimo"
  },
  {
    "testo": "La legge è uguale per tutti: questa è la promessa della civiltà.",
    "autore": "Anonimo"
  },
  {
    "testo": "L'equità è la giustizia in casi concreti.",
    "autore": "Aristotele"
  },
  {
    "testo": "Chi fa da sé fa per tre, ma chi sbaglia da sé paga per tre.",
    "autore": "Proverbio"
  },
  {
    "testo": "La vera giustizia guarda il cuore, non solo i fatti.",
    "autore": "Anonimo"
  },
  {
    "testo": "Chi non sa perdonare non sa giudicare.",
    "autore": "Proverbio"
  },
  {
    "testo": "Il progresso è impossibile senza cambiamento; chi non sa cambiare idea non sa cambiare niente.",
    "autore": "George Bernard Shaw"
  },
  {
    "testo": "Ogni progresso è il frutto di una domanda che qualcuno ha osato fare.",
    "autore": "Anonimo"
  },
  {
    "testo": "Non si va avanti guardando indietro.",
    "autore": "Proverbio"
  },
  {
    "testo": "Il progresso non è lineare: è una spirale che sale.",
    "autore": "Anonimo"
  },
  {
    "testo": "Chi si ferma al passato non costruisce futuro.",
    "autore": "Anonimo"
  },
  {
    "testo": "L'umanità progredisce sulla schiena delle generazioni precedenti.",
    "autore": "Proverbio"
  },
  {
    "testo": "Il vero progresso mette d'accordo scienza e coscienza.",
    "autore": "Anonimo"
  },
  {
    "testo": "Ogni invenzione è figlia della necessità e della fantasia.",
    "autore": "Anonimo"
  },
  {
    "testo": "Chi non rischia non innova.",
    "autore": "Anonimo"
  },
  {
    "testo": "Il futuro appartiene a chi lo prepara oggi.",
    "autore": "Anonimo"
  },
  {
    "testo": "L'importante non è vincere, ma partecipare.",
    "autore": "Pierre de Coubertin"
  },
  {
    "testo": "Lo sport è la guerra senza armi.",
    "autore": "George Orwell"
  },
  {
    "testo": "Chi non gioca non può vincere.",
    "autore": "Proverbio"
  },
  {
    "testo": "La sconfitta è la vittoria che non ha ancora capito di esserlo.",
    "autore": "Anonimo"
  },
  {
    "testo": "Lo sport insegna a perdere con dignità e vincere con umiltà.",
    "autore": "Anonimo"
  },
  {
    "testo": "Il campione non è chi non cade mai, ma chi si rialza sempre.",
    "autore": "Anonimo"
  },
  {
    "testo": "La forma è temporanea, la classe è permanente.",
    "autore": "Proverbio calcistico"
  },
  {
    "testo": "Nel gioco della vita, il lavoro di squadra è tutto.",
    "autore": "Anonimo"
  },
  {
    "testo": "Chi si allena nella tempesta danza sotto la pioggia.",
    "autore": "Anonimo"
  },
  {
    "testo": "La vittoria più bella è quella ottenuta dopo la sconfitta più dura.",
    "autore": "Anonimo"
  },
  {
    "testo": "Il dolore è necessario; la sofferenza è una scelta.",
    "autore": "Proverbio buddhista"
  },
  {
    "testo": "Le ferite fanno male finché non le guardi in faccia.",
    "autore": "Anonimo"
  },
  {
    "testo": "Il dolore non vissuto si trasmette.",
    "autore": "Psicologia moderna"
  },
  {
    "testo": "Guarire significa diventare interi, non tornare come prima.",
    "autore": "Anonimo"
  },
  {
    "testo": "Chi accetta il dolore impara da esso; chi lo fugge lo porta per sempre.",
    "autore": "Anonimo"
  },
  {
    "testo": "Le lacrime sono la preghiera sillenziosa dell'anima.",
    "autore": "Proverbio"
  },
  {
    "testo": "Il tempo non guarisce: sei tu che guarisci nel tempo.",
    "autore": "Anonimo"
  },
  {
    "testo": "Dalla rottura nasce la luce.",
    "autore": "Leonard Cohen"
  },
  {
    "testo": "Il dolore condiviso si dimezza; la gioia condivisa si raddoppia.",
    "autore": "Proverbio svedese"
  },
  {
    "testo": "Non si guarisce da ciò che non si è disposti a sentire.",
    "autore": "Anonimo"
  },
  {
    "testo": "La giovinezza è un dono della natura; la vecchiaia è un'opera d'arte.",
    "autore": "Garson Kanin"
  },
  {
    "testo": "Chi invecchia con grazia ha vissuto con stile.",
    "autore": "Anonimo"
  },
  {
    "testo": "I capelli bianchi sono la corona della vita ben vissuta.",
    "autore": "Proverbio"
  },
  {
    "testo": "Con l'età si impara che la pazienza non è rassegnazione.",
    "autore": "Anonimo"
  },
  {
    "testo": "La saggezza degli anni vale più del vigore della giovinezza.",
    "autore": "Proverbio"
  },
  {
    "testo": "Chi ha vissuto a lungo ha il dovere di trasmettere.",
    "autore": "Proverbio"
  },
  {
    "testo": "L'anziano è una biblioteca vivente.",
    "autore": "Proverbio africano"
  },
  {
    "testo": "Non invecchiare: maturare.",
    "autore": "Anonimo"
  },
  {
    "testo": "Chi ha visto molti inverni conosce il valore della primavera.",
    "autore": "Proverbio"
  },
  {
    "testo": "La terza età è l'età della libertà interiore.",
    "autore": "Anonimo"
  },
  {
    "testo": "L'amico è colui che entra quando tutti gli altri escono.",
    "autore": "Walter Winchell"
  },
  {
    "testo": "Un amico è un'altra metà di sé.",
    "autore": "Aristotele"
  },
  {
    "testo": "Chi ha un vero amico ha un tesoro inestimabile.",
    "autore": "Proverbio"
  },
  {
    "testo": "L'amicizia è la forma più alta dell'amore perché non chiede nulla in cambio.",
    "autore": "Anonimo"
  },
  {
    "testo": "Un amico che ti dice la verità vale più di mille che ti lusingano.",
    "autore": "Proverbio"
  },
  {
    "testo": "I veri amici si riconoscono nelle difficoltà.",
    "autore": "Proverbio italiano"
  },
  {
    "testo": "Chi ha molti amici non ha amici veri.",
    "autore": "Aristotele"
  },
  {
    "testo": "L'amicizia è come il vino: migliora con gli anni.",
    "autore": "Proverbio"
  },
  {
    "testo": "Un'amicizia che finisce non è mai davvero iniziata.",
    "autore": "Proverbio"
  },
  {
    "testo": "Chi trova un amico trova una seconda anima.",
    "autore": "Proverbio"
  },
  {
    "testo": "Non si può scoprire nuovi oceani se non si ha il coraggio di perdere di vista la riva.",
    "autore": "André Gide"
  },
  {
    "testo": "Il mare non conosce frontiere.",
    "autore": "Proverbio marinaro"
  },
  {
    "testo": "Chi ha il mare nel cuore non è mai lontano da casa.",
    "autore": "Anonimo"
  },
  {
    "testo": "Navigare è necessario; vivere non è necessario.",
    "autore": "Pompeo Magno / Fernando Pessoa"
  },
  {
    "testo": "Il porto più sicuro è quello che non si raggiunge mai.",
    "autore": "Proverbio marinaro"
  },
  {
    "testo": "Chi non ha mai visto il mare non ha visto la grandezza del mondo.",
    "autore": "Anonimo"
  },
  {
    "testo": "Le tempeste si superano non aspettandole, ma navigando.",
    "autore": "Proverbio marinaro"
  },
  {
    "testo": "Il mare insegna l'umiltà: sei sempre piccolo davanti a lui.",
    "autore": "Anonimo"
  },
  {
    "testo": "Chi ha l'orizzonte negli occhi non smette mai di cercare.",
    "autore": "Anonimo"
  },
  {
    "testo": "Ogni porto è il punto di partenza di un nuovo viaggio.",
    "autore": "Proverbio"
  },
  {
    "testo": "L'onestà è il dono più raro che puoi fare agli altri.",
    "autore": "Anonimo"
  },
  {
    "testo": "Chi dice sempre la verità non ha bisogno di buona memoria.",
    "autore": "Mark Twain"
  },
  {
    "testo": "Una bugia può fare il giro del mondo mentre la verità si allaccia le scarpe.",
    "autore": "Mark Twain"
  },
  {
    "testo": "L'onestà non premia sempre nell'immediato, ma premia sempre nel lungo periodo.",
    "autore": "Anonimo"
  },
  {
    "testo": "Chi tradisce la fiducia tradisce se stesso.",
    "autore": "Proverbio"
  },
  {
    "testo": "La disonestà è il modo più veloce di diventare povero.",
    "autore": "Anonimo"
  },
  {
    "testo": "Chi è onesto con se stesso può essere onesto con tutti.",
    "autore": "Anonimo"
  },
  {
    "testo": "La verità fa male, ma guarisce. La menzogna accarezza, ma avvelena.",
    "autore": "Proverbio"
  },
  {
    "testo": "Chi vive nell'inganno vive nella paura.",
    "autore": "Anonimo"
  },
  {
    "testo": "L'integrità è ciò che fai quando nessuno ti guarda.",
    "autore": "C.S. Lewis"
  },
  {
    "testo": "Il silenzio è l'eloquenza del dolore.",
    "autore": "Lord Byron"
  },
  {
    "testo": "Nel silenzio si sente la voce dell'anima.",
    "autore": "Anonimo"
  },
  {
    "testo": "Chi sa stare in silenzio sa ascoltare.",
    "autore": "Proverbio"
  },
  {
    "testo": "Il silenzio è il suono più puro che esista.",
    "autore": "Anonimo"
  },
  {
    "testo": "Alcune cose si capiscono meglio nel silenzio.",
    "autore": "Anonimo"
  },
  {
    "testo": "Il silenzio è la porta della saggezza.",
    "autore": "Proverbio orientale"
  },
  {
    "testo": "Chi parla troppo lascia poco spazio alla verità.",
    "autore": "Proverbio"
  },
  {
    "testo": "Il silenzio scelto è potere; il silenzio subìto è debolezza.",
    "autore": "Anonimo"
  },
  {
    "testo": "Nelle parole c'è l'uomo; nel silenzio c'è il saggio.",
    "autore": "Proverbio"
  },
  {
    "testo": "Il silenzio condiviso con chi ami vale più di mille conversazioni.",
    "autore": "Anonimo"
  },
  {
    "testo": "Ogni vita è un romanzo: scrivi il capitolo di oggi.",
    "autore": "Anonimo"
  },
  {
    "testo": "Non esistono vite inutili: esistono vite non ancora comprese.",
    "autore": "Anonimo"
  },
  {
    "testo": "Chi ha vissuto amando non ha vissuto invano.",
    "autore": "Anonimo"
  },
  {
    "testo": "Il senso della vita non si trova: si crea ogni giorno.",
    "autore": "Jean-Paul Sartre"
  },
  {
    "testo": "La vita è degna di essere vissuta finché c'è qualcuno che ti ama e qualcosa che ami fare.",
    "autore": "Anonimo"
  },
  {
    "testo": "Non aspettare il tramonto per dire che la giornata è stata bella.",
    "autore": "Anonimo"
  },
  {
    "testo": "Chi ha dato tutto ha vissuto tutto.",
    "autore": "Anonimo"
  },
  {
    "testo": "La vita è troppo bella per essere vissuta in modo mediocre.",
    "autore": "Anonimo"
  },
  {
    "testo": "Non smettere mai di essere curioso: è il segreto di chi rimane vivo dentro.",
    "autore": "Anonimo"
  },
  {
    "testo": "Chi porta amore, luce e speranza ha trovato il senso della vita.",
    "autore": "Anonimo"
  },
  {
    "testo": "Chi tratta gli altri come vorrebbe essere trattato non sbaglia mai.",
    "autore": "Proverbio universale"
  },
  {
    "testo": "Le relazioni sono lo specchio in cui ci vediamo per come siamo davvero.",
    "autore": "Anonimo"
  },
  {
    "testo": "Chi sa amare le imperfezioni degli altri sa amare la vita.",
    "autore": "Anonimo"
  },
  {
    "testo": "Non cercare l'anima gemella: diventa tu l'anima gemella di qualcuno.",
    "autore": "Anonimo"
  },
  {
    "testo": "Chi investe nelle relazioni investe nella felicità.",
    "autore": "Anonimo"
  },
  {
    "testo": "Le parole dure feriscono; le parole gentili guariscono.",
    "autore": "Proverbio"
  },
  {
    "testo": "Chi sa chiedere scusa è più forte di chi non sbaglia mai.",
    "autore": "Anonimo"
  },
  {
    "testo": "La fiducia si costruisce con mille azioni e si distrugge con una.",
    "autore": "Anonimo"
  },
  {
    "testo": "Chi porta presenza alle relazioni porta il dono più raro.",
    "autore": "Anonimo"
  },
  {
    "testo": "Non contare gli amici: pesa la qualità dell'amicizia.",
    "autore": "Proverbio"
  },
  {
    "testo": "Chi sa essere presente nei dolori altrui è un amico vero.",
    "autore": "Anonimo"
  },
  {
    "testo": "Le relazioni più belle nascono dalla libertà, non dalla dipendenza.",
    "autore": "Anonimo"
  },
  {
    "testo": "Chi porta rispetto alle relazioni porta cura al cuore.",
    "autore": "Anonimo"
  },
  {
    "testo": "L'amore vero si vede nella quotidianità, non nelle grandi occasioni.",
    "autore": "Anonimo"
  },
  {
    "testo": "Chi sa ricevere aiuto sa anche darlo.",
    "autore": "Proverbio"
  },
  {
    "testo": "La solitudine è il prezzo della grandezza.",
    "autore": "Proverbio"
  },
  {
    "testo": "Chi non sa stare solo non è mai davvero insieme agli altri.",
    "autore": "Paul Tillich"
  },
  {
    "testo": "La solitudine abitata è più ricca della compagnia vuota.",
    "autore": "Anonimo"
  },
  {
    "testo": "Chi teme la solitudine teme se stesso.",
    "autore": "Anonimo"
  },
  {
    "testo": "Nella solitudine si sente la musica dell'anima.",
    "autore": "Anonimo"
  },
  {
    "testo": "La solitudine è un'amica quando sai come viverla.",
    "autore": "Proverbio"
  },
  {
    "testo": "Chi impara ad amarsi nella solitudine impara ad amare gli altri nella compagnia.",
    "autore": "Anonimo"
  },
  {
    "testo": "Il silenzio della solitudine è il laboratorio dei grandi pensieri.",
    "autore": "Anonimo"
  },
  {
    "testo": "Chi sceglie la solitudine trova se stesso; chi la subisce si perde.",
    "autore": "Anonimo"
  },
  {
    "testo": "La solitudine creativa è il più fecondo dei silenzi.",
    "autore": "Anonimo"
  },
  {
    "testo": "La forza vera non si vede: si sente.",
    "autore": "Proverbio"
  },
  {
    "testo": "Chi porta forza interiore non ha bisogno di dimostrarla.",
    "autore": "Anonimo"
  },
  {
    "testo": "La forza nasce dove finisce la paura di essere deboli.",
    "autore": "Anonimo"
  },
  {
    "testo": "Chi conosce la propria debolezza conosce la propria forza.",
    "autore": "Proverbio cinese"
  },
  {
    "testo": "La forza di carattere si vede nelle piccole rinunce quotidiane.",
    "autore": "Anonimo"
  },
  {
    "testo": "Chi porta calma nella tempesta è il più forte.",
    "autore": "Proverbio"
  },
  {
    "testo": "La forza vera è nella gentilezza persistente.",
    "autore": "Anonimo"
  },
  {
    "testo": "Chi non si lascia abbattere dalle circostanze è padrone del destino.",
    "autore": "Anonimo"
  },
  {
    "testo": "La forza interiore si coltiva nel silenzio e nella disciplina.",
    "autore": "Anonimo"
  },
  {
    "testo": "Chi porta forza agli altri trova la propria forza moltiplicata.",
    "autore": "Anonimo"
  },
  {
    "testo": "Il tempo è il fiume in cui nuotiamo: non si può tornare indietro.",
    "autore": "Anonimo"
  },
  {
    "testo": "Chi usa bene il tempo usa bene la vita.",
    "autore": "Benjamin Franklin"
  },
  {
    "testo": "Non perdere tempo a cercare il tempo perduto.",
    "autore": "Proverbio"
  },
  {
    "testo": "Il tempo non aspetta nessuno: sii tu ad aspettarlo.",
    "autore": "Anonimo"
  },
  {
    "testo": "Chi rispetta il tempo degli altri si fa rispettare.",
    "autore": "Proverbio"
  },
  {
    "testo": "Il tempo libero è il tempo in cui diventi chi sei davvero.",
    "autore": "Aristotele"
  },
  {
    "testo": "Non rimpiantere il tempo passato: usalo come mappa del futuro.",
    "autore": "Anonimo"
  },
  {
    "testo": "Chi vive senza fretta vive più pienamente.",
    "autore": "Anonimo"
  },
  {
    "testo": "Il tempo è l'unica risorsa che non si può guadagnare: usala bene.",
    "autore": "Anonimo"
  },
  {
    "testo": "Chi non spreca il tempo non spreca la vita.",
    "autore": "Proverbio"
  },
  {
    "testo": "Chi non ha valori non ha direzione.",
    "autore": "Anonimo"
  },
  {
    "testo": "I valori non si dichiarano: si dimostrano con le azioni.",
    "autore": "Anonimo"
  },
  {
    "testo": "Chi tradisce i propri valori si tradisce.",
    "autore": "Anonimo"
  },
  {
    "testo": "Chi porta entusiasmo rende ogni compito straordinario.",
    "autore": "Anonimo"
  },
  {
    "testo": "La vita non è una prova generale: è già la prima.",
    "autore": "Anonimo"
  },
  {
    "testo": "Chi sa aspettare sa vivere.",
    "autore": "Proverbio"
  },
  {
    "testo": "Non esistono persone noiose: esistono persone non ancora conosciute abbastanza.",
    "autore": "Anonimo"
  },
  {
    "testo": "La vita è fatta di connessioni: coltivale.",
    "autore": "Anonimo"
  },
  {
    "testo": "Chi porta curiosità al mondo lo trova sempre interessante.",
    "autore": "Anonimo"
  },
  {
    "testo": "Non aver paura di ricominciare: ogni inizio è un dono.",
    "autore": "Anonimo"
  },
  {
    "testo": "Chi porta gentilezza semina bellezza ovunque va.",
    "autore": "Anonimo"
  },
  {
    "testo": "La vita è generosa con chi è generoso verso di essa.",
    "autore": "Proverbio"
  },
  {
    "testo": "Non aspettare che arrivi la fortuna: prepara il terreno.",
    "autore": "Anonimo"
  },
  {
    "testo": "Chi porta rispetto alla propria storia rispetta il proprio futuro.",
    "autore": "Anonimo"
  },
  {
    "testo": "La vita è piena di strade: scegli quella che ti fa crescere.",
    "autore": "Anonimo"
  },
  {
    "testo": "Non smettere mai di fare domande: sono il carburante della mente.",
    "autore": "Anonimo"
  },
  {
    "testo": "Chi porta chiarezza al caos porta un dono inestimabile.",
    "autore": "Anonimo"
  },
  {
    "testo": "La vita è bella quando la vivi con gli occhi aperti.",
    "autore": "Anonimo"
  },
  {
    "testo": "Non aspettare che gli altri cambino: sii tu il cambiamento.",
    "autore": "Anonimo"
  },
  {
    "testo": "Chi porta cura al proprio spirito porta cura al mondo.",
    "autore": "Anonimo"
  },
  {
    "testo": "La vita è un'opera in divenire: continua a lavorarci ogni giorno.",
    "autore": "Anonimo"
  },
  {
    "testo": "Non smettere mai di credere: la fede muove montagne interiori.",
    "autore": "Anonimo"
  },
  {
    "testo": "Chi porta passione alla quotidianità trasforma il comune in straordinario.",
    "autore": "Anonimo"
  },
  {
    "testo": "La vita è ricca di possibilità per chi sa aprire gli occhi.",
    "autore": "Anonimo"
  },
  {
    "testo": "Non aspettare che arrivi il momento perfetto: rendilo perfetto tu.",
    "autore": "Anonimo"
  },
  {
    "testo": "Chi porta amore al lavoro porta gioia alla vita.",
    "autore": "Anonimo"
  },
  {
    "testo": "La vita è bella perché è diversa ogni giorno.",
    "autore": "Anonimo"
  },
  {
    "testo": "Non smettere mai di crescere: è il segno più bello dell'essere vivi.",
    "autore": "Anonimo"
  },
  {
    "testo": "Chi porta luce interiore non ha paura del buio esteriore.",
    "autore": "Anonimo"
  },
  {
    "testo": "La vita è un viaggio che vale ogni singolo passo.",
    "autore": "Anonimo"
  },
  {
    "testo": "Non aspettare che qualcuno ti salvi: salva te stesso prima.",
    "autore": "Anonimo"
  },
  {
    "testo": "Chi porta cura alle piccole cose porta eccellenza alle grandi.",
    "autore": "Anonimo"
  },
  {
    "testo": "La vita è troppo preziosa per essere vissuta distrattamente.",
    "autore": "Anonimo"
  },
  {
    "testo": "Non smettere mai di amare: è l'unica cosa che cresce donandola.",
    "autore": "Anonimo"
  },
  {
    "testo": "Chi porta pace al mondo inizia dalla pace con se stesso.",
    "autore": "Anonimo"
  },
  {
    "testo": "La vita è bella anche quando non lo sembra: cerca la bellezza nascosta.",
    "autore": "Anonimo"
  },
  {
    "testo": "Non aspettare l'alba per iniziare: ogni momento è l'alba di qualcosa.",
    "autore": "Anonimo"
  },
  {
    "testo": "Chi porta rispetto alla vita altrui eleva la propria.",
    "autore": "Anonimo"
  }
]